{"SI":"cad04e6462d0724d0e739b28a458cf447df9b193","PI":"14060","CD":"20160814044629","P":[{"R":{"RP":{"x":-3.96,"y":-20.5,"z":4.31},"LP":{"x":-3.7,"y":-20.74,"z":5.24}},"RT":0.07},{"R":{"RP":{"x":-2.64,"y":-21.72,"z":4.33},"LP":{"x":-2.37,"y":-21.92,"z":5.27}},"RT":0.16},{"R":{"RP":{"x":-0.92,"y":-22.52,"z":4.42},"LP":{"x":-0.65,"y":-22.66,"z":5.38}},"RT":0.27},{"R":{"RP":{"x":0.43,"y":-22.72,"z":4.55},"LP":{"x":0.69,"y":-22.82,"z":5.51}},"RT":0.34},{"R":{"RP":{"x":2.63,"y":-22.34,"z":4.9},"LP":{"x":2.85,"y":-22.38,"z":5.87}},"RT":0.46},{"R":{"RP":{"x":4.2,"y":-21.42,"z":5.3},"LP":{"x":4.37,"y":-21.42,"z":6.28}},"RT":0.56},{"R":{"RP":{"x":5.29,"y":-20.25,"z":5.73},"LP":{"x":5.42,"y":-20.24,"z":6.72}},"RT":0.65},{"R":{"RP":{"x":6.27,"y":-18.17,"z":6.45},"LP":{"x":6.33,"y":-18.15,"z":7.45}},"RT":0.76},{"R":{"RP":{"x":6.5,"y":-16.1,"z":7.18},"LP":{"x":6.51,"y":-16.08,"z":8.18}},"RT":0.87},{"R":{"RP":{"x":6.13,"y":-13.99,"z":7.95},"LP":{"x":6.09,"y":-14.0,"z":8.95}},"RT":0.97},{"R":{"RP":{"x":5.24,"y":-12.09,"z":8.7},"LP":{"x":5.15,"y":-12.14,"z":9.69}},"RT":1.06},{"R":{"RP":{"x":3.76,"y":-10.32,"z":9.49},"LP":{"x":3.65,"y":-10.43,"z":10.48}},"RT":1.16},{"R":{"RP":{"x":1.71,"y":-8.88,"z":10.28},"LP":{"x":1.59,"y":-9.04,"z":11.26}},"RT":1.27},{"R":{"RP":{"x":-0.32,"y":-8.09,"z":10.91},"LP":{"x":-0.44,"y":-8.31,"z":11.88}},"RT":1.36},{"R":{"RP":{"x":-2.74,"y":-7.76,"z":11.51},"LP":{"x":-2.84,"y":-8.03,"z":12.47}},"RT":1.47},{"R":{"RP":{"x":-5.16,"y":-8.04,"z":12.01},"LP":{"x":-5.22,"y":-8.35,"z":12.96}},"RT":1.57},{"R":{"RP":{"x":-7.06,"y":-8.73,"z":12.34},"LP":{"x":-7.08,"y":-9.07,"z":13.28}},"RT":1.66},{"R":{"RP":{"x":-8.54,"y":-9.68,"z":12.56},"LP":{"x":-8.52,"y":-10.04,"z":13.49}},"RT":1.74},{"R":{"RP":{"x":-10.26,"y":-11.61,"z":12.78},"LP":{"x":-10.16,"y":-11.98,"z":13.7}},"RT":1.87},{"R":{"RP":{"x":-10.94,"y":-13.22,"z":12.85},"LP":{"x":-10.79,"y":-13.57,"z":13.77}},"RT":1.97},{"R":{"RP":{"x":-11.1,"y":-14.53,"z":12.88},"LP":{"x":-10.91,"y":-14.86,"z":13.8}},"RT":2.05},{"R":{"RP":{"x":-10.7,"y":-16.33,"z":12.89},"LP":{"x":-10.47,"y":-16.61,"z":13.82}},"RT":2.16},{"R":{"RP":{"x":-9.77,"y":-17.59,"z":12.91},"LP":{"x":-9.51,"y":-17.82,"z":13.85}},"RT":2.27},{"R":{"RP":{"x":-8.36,"y":-18.38,"z":12.98},"LP":{"x":-8.09,"y":-18.55,"z":13.92}},"RT":2.37},{"R":{"RP":{"x":-6.92,"y":-18.58,"z":13.1},"LP":{"x":-6.66,"y":-18.69,"z":14.05}},"RT":2.46},{"R":{"RP":{"x":-5.19,"y":-18.21,"z":13.32},"LP":{"x":-4.95,"y":-18.27,"z":14.29}},"RT":2.57},{"R":{"RP":{"x":-3.36,"y":-17.07,"z":13.69},"LP":{"x":-3.16,"y":-17.09,"z":14.67}},"RT":2.68},{"R":{"RP":{"x":-2.19,"y":-15.78,"z":14.06},"LP":{"x":-2.03,"y":-15.77,"z":15.05}},"RT":2.76},{"R":{"RP":{"x":-1.14,"y":-13.83,"z":14.58},"LP":{"x":-1.04,"y":-13.8,"z":15.58}},"RT":2.86},{"R":{"RP":{"x":-0.56,"y":-11.5,"z":15.21},"LP":{"x":-0.51,"y":-11.47,"z":16.21}},"RT":2.96},{"R":{"RP":{"x":-0.54,"y":-8.95,"z":15.91},"LP":{"x":-0.55,"y":-8.94,"z":16.91}},"RT":3.06},{"R":{"RP":{"x":-1.1,"y":-6.4,"z":16.64},"LP":{"x":-1.16,"y":-6.43,"z":17.63}},"RT":3.17},{"R":{"RP":{"x":-2.2,"y":-4.05,"z":17.36},"LP":{"x":-2.3,"y":-4.12,"z":18.35}},"RT":3.26},{"R":{"RP":{"x":-3.83,"y":-1.93,"z":18.08},"LP":{"x":-3.94,"y":-2.05,"z":19.07}},"RT":3.37},{"R":{"RP":{"x":-5.74,"y":-0.31,"z":18.72},"LP":{"x":-5.86,"y":-0.48,"z":19.69}},"RT":3.46},{"R":{"RP":{"x":-7.93,"y":0.86,"z":19.29},"LP":{"x":-8.05,"y":0.63,"z":20.26}},"RT":3.56},{"R":{"RP":{"x":-10.25,"y":1.48,"z":19.78},"LP":{"x":-10.34,"y":1.2,"z":20.73}},"RT":3.66},{"R":{"RP":{"x":-12.45,"y":1.53,"z":20.14},"LP":{"x":-12.5,"y":1.21,"z":21.08}},"RT":3.77},{"R":{"RP":{"x":-14.27,"y":1.1,"z":20.37},"LP":{"x":-14.27,"y":0.74,"z":21.31}},"RT":3.86},{"R":{"RP":{"x":-15.73,"y":0.26,"z":20.51},"LP":{"x":-15.68,"y":-0.1,"z":21.43}},"RT":3.96},{"R":{"RP":{"x":-16.75,"y":-0.94,"z":20.55},"LP":{"x":-16.64,"y":-1.31,"z":21.47}},"RT":4.07},{"R":{"RP":{"x":-17.1,"y":-2.14,"z":20.51},"LP":{"x":-16.94,"y":-2.48,"z":21.44}},"RT":4.16}]}